simpletail/__init__.py
tests/__init__.py
tests/test_ropen.py
simpletail-1.0.0.dist-info/LICENSE.txt
simpletail-1.0.0.dist-info/METADATA
simpletail-1.0.0.dist-info/WHEEL
simpletail-1.0.0.dist-info/top_level.txt
simpletail-1.0.0.dist-info/RECORD
